telugu_stopwords/__init__.py
telugu_stopwords/telugu_stopwords.py
telugu_stopwords-0.1.1.dist-info/licenses/LICENSE
telugu_stopwords-0.1.1.dist-info/METADATA
telugu_stopwords-0.1.1.dist-info/WHEEL
telugu_stopwords-0.1.1.dist-info/top_level.txt
telugu_stopwords-0.1.1.dist-info/RECORD
