Metadata-Version: 2.4
Name: telugu-stopwords
Version: 0.1.1
Summary: A Python package for managing Telugu stop words.
Author-email: Pavan Yellathakota <pavanyellathakota@gmail.com>, Prudhvi Yellathakota <prudhviyellathakota@gmail.com>
License-Expression: MIT
Project-URL: Homepage, https://github.com/PavanYellathakota/telugu-stopwords
Project-URL: Repository, https://github.com/PavanYellathakota/telugu-stopwords
Requires-Python: >=3.7
License-File: LICENSE
Dynamic: license-file
